fireraven/__init__.py
fireraven/dummy.py
fireraven-0.1.0.dist-info/LICENSE
fireraven-0.1.0.dist-info/METADATA
fireraven-0.1.0.dist-info/WHEEL
fireraven-0.1.0.dist-info/top_level.txt
fireraven-0.1.0.dist-info/RECORD
